tests/__init__.py
tests/test_objective.py
wrapdisc/__init__.py
wrapdisc/var.py
wrapdisc/wrapdisc.py
wrapdisc/util/__init__.py
wrapdisc/util/float.py
wrapdisc-2.5.0.dist-info/LICENSE
wrapdisc-2.5.0.dist-info/METADATA
wrapdisc-2.5.0.dist-info/WHEEL
wrapdisc-2.5.0.dist-info/top_level.txt
wrapdisc-2.5.0.dist-info/RECORD
