Metadata-Version: 2.1
Name: wrapdisc
Version: 2.5.0
Summary: Optimize both discrete and continuous variables using just a continuous optimizer such as in scipy.optimize
Home-page: https://github.com/impredicative/wrapdisc/
Author: Ouroboros Chrysopoeia
Author-email: impredicative@users.noreply.github.com
License: UNKNOWN
Keywords: optimization discrete continuous scipy.optimize wrapper
Platform: UNKNOWN
Classifier: Programming Language :: Python :: 3.10
Classifier: License :: OSI Approved :: GNU Affero General Public License v3
Classifier: Topic :: Scientific/Engineering :: Mathematics
Classifier: Topic :: Scientific/Engineering :: Information Analysis
Classifier: Topic :: Software Development :: Libraries :: Python Modules
Requires-Python: >=3.10
License-File: LICENSE
